aldryn_reversion/__init__.py
aldryn_reversion/admin.py
aldryn_reversion/core.py
aldryn_reversion/forms.py
aldryn_reversion/utils.py
aldryn_reversion/templates/aldryn_reversion/confirm_recover.html
aldryn_reversion/templates/aldryn_reversion/confirm_reversion.html
aldryn_reversion/test_helpers/__init__.py
aldryn_reversion/test_helpers/project/__init__.py
aldryn_reversion/test_helpers/project/test_app/__init__.py
aldryn_reversion/test_helpers/project/test_app/admin.py
aldryn_reversion/test_helpers/project/test_app/cms_plugins.py
aldryn_reversion/test_helpers/project/test_app/models.py
aldryn_reversion/tests/__init__.py
aldryn_reversion/tests/base.py
aldryn_reversion/tests/test_admin_views.py
aldryn_reversion/tests/test_forms.py
aldryn_reversion/tests/test_placeholders.py
aldryn_reversion/tests/test_utils.py
aldryn_reversion-1.1.0.dist-info/DESCRIPTION.rst
aldryn_reversion-1.1.0.dist-info/METADATA
aldryn_reversion-1.1.0.dist-info/RECORD
aldryn_reversion-1.1.0.dist-info/WHEEL
aldryn_reversion-1.1.0.dist-info/metadata.json
aldryn_reversion-1.1.0.dist-info/top_level.txt
