Metadata-Version: 2.0
Name: aldryn-reversion
Version: 1.1.0
Summary: Support for django-reversion on models with translatable fields and django-cms placeholder fields.
Home-page: https://github.com/aldryn/aldryn-reversion
Author: Divio AG
Author-email: info@divio.ch
License: LICENSE.txt
Platform: OS Independent
Classifier: Development Status :: 5 - Production/Stable
Classifier: Environment :: Web Environment
Classifier: Framework :: Django
Classifier: Framework :: Django :: 1.6
Classifier: Framework :: Django :: 1.7
Classifier: Framework :: Django :: 1.8
Classifier: Framework :: Django :: 1.9
Classifier: Intended Audience :: Developers
Classifier: License :: OSI Approved :: BSD License
Classifier: Operating System :: OS Independent
Classifier: Programming Language :: Python
Classifier: Programming Language :: Python :: 2.6
Classifier: Programming Language :: Python :: 2.7
Classifier: Programming Language :: Python :: 3.4
Classifier: Programming Language :: Python :: 3.5
Classifier: Topic :: Internet :: WWW/HTTP :: Dynamic Content
Classifier: Topic :: Software Development
Classifier: Topic :: Software Development :: Libraries :: Application Frameworks
Requires-Dist: Django (<1.11,>=1.6)
Requires-Dist: django-cms (>=3.0.12)
Requires-Dist: django-reversion (>=1.8.2,<1.11)
